acorn/__init__.py
acorn/acorn.abi3.so
acorn_py-0.1.31.dist-info/METADATA
acorn_py-0.1.31.dist-info/WHEEL
acorn_py-0.1.31.dist-info/RECORD
