Metadata-Version: 2.4
Name: acorn-py
Version: 0.1.31
Classifier: Development Status :: 1 - Planning
Classifier: Intended Audience :: Developers
Classifier: Intended Audience :: Information Technology
Classifier: Intended Audience :: Science/Research
Classifier: License :: OSI Approved :: MIT License
Classifier: Operating System :: POSIX :: Linux
Classifier: Operating System :: MacOS
Classifier: Operating System :: Microsoft :: Windows
Classifier: Natural Language :: English
Classifier: Programming Language :: Python
Classifier: Programming Language :: Rust
Classifier: Topic :: Scientific/Engineering
Summary: Python bindings for acorn-lib crate
Keywords: research,automation
Author-email: Jason Wohlgemuth <wohlgemuthjh@ornl.gov>
License-Expression: MIT
Requires-Python: >=3.10
Project-URL: Repository, https://code.ornl.gov/research-enablement/acorn.git
Project-URL: Changelog, https://code.ornl.gov/research-enablement/acorn/-/blob/main/CHANGELOG.md
